simple_gradient/Text_Gradient.py
simple_gradient-1.0.0.dist-info/LICENSE
simple_gradient-1.0.0.dist-info/METADATA
simple_gradient-1.0.0.dist-info/WHEEL
simple_gradient-1.0.0.dist-info/top_level.txt
simple_gradient-1.0.0.dist-info/RECORD
